ambee/__init__.py
ambee/ambee.py
ambee/exceptions.py
ambee/models.py
ambee/py.typed
ambee-0.4.0.dist-info/LICENSE.md
ambee-0.4.0.dist-info/WHEEL
ambee-0.4.0.dist-info/METADATA
ambee-0.4.0.dist-info/RECORD
