Metadata-Version: 2.1
Name: ambee
Version: 0.4.0
Summary: Asynchronous Python client for the Ambee API.
Home-page: https://github.com/frenck/python-ambee
License: MIT
Keywords: ambee,api,async,client
Author: Franck Nijhof
Author-email: opensource@frenck.dev
Maintainer: Franck Nijhof
Maintainer-email: opensource@frenck.dev
Requires-Python: >=3.8,<4.0
Classifier: Development Status :: 4 - Beta
Classifier: Framework :: AsyncIO
Classifier: Intended Audience :: Developers
Classifier: License :: OSI Approved :: MIT License
Classifier: Natural Language :: English
Classifier: Programming Language :: Python :: 3
Classifier: Programming Language :: Python :: 3.10
Classifier: Programming Language :: Python :: 3.8
Classifier: Programming Language :: Python :: 3.9
Classifier: Topic :: Software Development :: Libraries :: Python Modules
Requires-Dist: aiohttp (>=3.0.0)
Requires-Dist: yarl (>=1.6.0)
Project-URL: Bug Tracker, https://github.com/frenck/python-ambee/issues
Project-URL: Changelog, https://github.com/frenck/python-ambee/releases
Project-URL: Documentation, https://github.com/frenck/python-ambee
Project-URL: Repository, https://github.com/frenck/python-ambee
